curseforge/__init__.py
curseforge/api.py
curseforge/enums.py
curseforge/utils.py
PyCurseForge-1.0.0.post2.dist-info/LICENSE.md
PyCurseForge-1.0.0.post2.dist-info/METADATA
PyCurseForge-1.0.0.post2.dist-info/WHEEL
PyCurseForge-1.0.0.post2.dist-info/top_level.txt
PyCurseForge-1.0.0.post2.dist-info/RECORD
