Metadata-Version: 2.1
Name: PyCurseForge
Version: 1.0.0.post2
Summary: A python wrapper for the (hidden) CurseForge API
Home-page: https://github.com/XuaTheGrate/PyCurseForge
Author: XuaTheGrate
License: MIT
Platform: UNKNOWN
Classifier: Development Status :: 2 - Pre-Alpha
Classifier: Intended Audience :: Developers
Classifier: License :: OSI Approved :: MIT License
Classifier: Natural Language :: English
Classifier: Operating System :: OS Independent
Classifier: Programming Language :: Python :: 3.8
Classifier: Programming Language :: Python :: 3.9
Classifier: Topic :: Games/Entertainment
Classifier: Topic :: Internet
Classifier: Topic :: Software Development :: Libraries
Classifier: Topic :: Software Development :: Libraries :: Python Modules
Classifier: Typing :: Typed
Requires-Python: >=3.8.0
Requires-Dist: requests (==2.26.0)
